Workbook

Sheet Productos
B5: ID | C5: PRODUCTO | D5: CATEGORIA | E5: PRECIO
B6: 1 | C6: MOUSE INALAMBRICO | D6: ACCESORIOS PC | E6: 45000
B7: 2 | C7: MOUSE GAMER | D7: ACCESORIOS PC | E7: 90000
B8: 3 | C8: TECLADO ALAMBRICO | D8: ACCESORIOS PC | E8: 60000
B9: 4 | C9: TECLADO MECANICO | D9: ACCESORIOS PC | E9: 220000
B10: 5 | C10: AUDIFONOS ALAMBRICOS | D10: AUDIO | E10: 35000
B11: 6 | C11: AUDIFONOS BLUETOOTH | D11: AUDIO | E11: 120000
B12: 7 | C12: DIADEMA GAMER | D12: AUDIO | E12: 180000
B13: 8 | C13: PARLANTE BLUETOOTH | D13: AUDIO | E13: 160000
B14: 9 | C14: MEMORIA USB 32GB | D14: ALMACENAMIENTO | E14: 35000
B15: 10 | C15: MEMORIA USB 64GB | D15: ALMACENAMIENTO | E15: 55000
B16: 11 | C16: DISCO SSD 480GB | D16: ALMACENAMIENTO | E16: 210000
B17: 12 | C17: DISCO SSD 1TB | D17: ALMACENAMIENTO | E17: 230000
... B35: 30 | C35: VIDRIO TEMPLADO | D35: ACCESORIOS MOVIL | E35: 20000

Sheet Ventas
B5: FECHA | C5: TICKET | D5: ID | E5: PRODUCTO | F5: CATEGORIA | G5: CANTIDAD | H5: PRECIO UNITARIO | I5: PRECIO TOTAL | J5: MEDIO_PAGO
B6: 46266 | C6: T-0001 | D6: 8 | E6: =VLOOKUP(D6,Productos!$B$6:$C$35,2,FALSE) -> PARLANTE BLUETOOTH | F6: =VLOOKUP(D6,Productos!$B$6:$D$35,3,FALSE) -> AUDIO | G6: 3 | H6: =VLOOKUP(D6,Productos!$B$6:$E$35,4,FALSE) -> 160000 | I6: =H6*G6 -> 480000 | J6: EFECTIVO
B7: 46268 | C7: T-0006 | D7: 21 | E7: =VLOOKUP(D7,Productos!$B$6:$C$35,2,FALSE) -> MONITOR 22' | F7: =VLOOKUP(D7,Productos!$B$6:$D$35,3,FALSE) -> MONITORES | G7: 5 | H7: =VLOOKUP(D7,Productos!$B$6:$E$35,4,FALSE) -> 520000 | I7: =H7*G7 -> 2600000 | J7: DAVIPLATA
B8: 46270 | C8: T-0007 | D8: 15 | E8: =VLOOKUP(D8,Productos!$B$6:$C$35,2,FALSE) -> CABLE USB-C | F8: =VLOOKUP(D8,Productos!$B$6:$D$35,3,FALSE) -> CABLES | G8: 3 | H8: =VLOOKUP(D8,Productos!$B$6:$E$35,4,FALSE) -> 30000 | I8: =H8*G8 -> 90000 | J8: NEQUI
B9: 46270 | C9: T-0008 | D9: 30 | E9: =VLOOKUP(D9,Productos!$B$6:$C$35,2,FALSE) -> VIDRIO TEMPLADO | F9: =VLOOKUP(D9,Productos!$B$6:$D$35,3,FALSE) -> ACCESORIOS MOVIL | G9: 1 | H9: =VLOOKUP(D9,Productos!$B$6:$E$35,4,FALSE) -> 20000 | I9: =H9*G9 -> 20000 | J9: EFECTIVO
B10: 46272 | C10: T-0009 | D10: 8 | E10: =VLOOKUP(D10,Productos!$B$6:$C$35,2,FALSE) -> PARLANTE BLUETOOTH | F10: =VLOOKUP(D10,Productos!$B$6:$D$35,3,FALSE) -> AUDIO | G10: 1 | H10: =VLOOKUP(D10,Productos!$B$6:$E$35,4,FALSE) -> 160000 | I10: =H10*G10 -> 160000 | J10: NEQUI
B11: 46272 | C11: T-0010 | D11: 7 | E11: =VLOOKUP(D11,Productos!$B$6:$C$35,2,FALSE) -> DIADEMA GAMER | F11: =VLOOKUP(D11,Productos!$B$6:$D$35,3,FALSE) -> AUDIO | G11: 2 | H11: =VLOOKUP(D11,Productos!$B$6:$E$35,4,FALSE) -> 180000 | I11: =H11*G11 -> 360000 | J11: EFECTIVO
B12: 46274 | C12: T-0011 | D12: 26 | E12: =VLOOKUP(D12,Productos!$B$6:$C$35,2,FALSE) -> SMARTWATCH BASICO | F12: =VLOOKUP(D12,Productos!$B$6:$D$35,3,FALSE) -> WEARABLES | G12: 4 | H12: =VLOOKUP(D12,Productos!$B$6:$E$35,4,FALSE) -> 180000 | I12: =H12*G12 -> 720000 | J12: EFECTIVO
B13: 46274 | C13: T-0012 | D13: 25 | E13: =VLOOKUP(D13,Productos!$B$6:$C$35,2,FALSE) -> PROTECTOR DE VOLTAJE | F13: =VLOOKUP(D13,Productos!$B$6:$D$35,3,FALSE) -> ENERGIA | G13: 5 | H13: =VLOOKUP(D13,Productos!$B$6:$E$35,4,FALSE) -> 80000 | I13: =H13*G13 -> 400000 | J13: TARJETA
B14: 46275 | C14: T-0013 | D14: 23 | E14: =VLOOKUP(D14,Productos!$B$6:$C$35,2,FALSE) -> TINTA GENERICA | F14: =VLOOKUP(D14,Productos!$B$6:$D$35,3,FALSE) -> HOGAR/OFICINA | G14: 5 | H14: =VLOOKUP(D14,Productos!$B$6:$E$35,4,FALSE) -> 90000 | I14: =H14*G14 -> 450000 | J14: DAVIPLATA
B15: 46277 | C15: T-0014 | D15: 12 | E15: =VLOOKUP(D15,Productos!$B$6:$C$35,2,FALSE) -> DISCO SSD 1TB | F15: =VLOOKUP(D15,Productos!$B$6:$D$35,3,FALSE) -> ALMACENAMIENTO | G15: 5 | H15: =VLOOKUP(D15,Productos!$B$6:$E$35,4,FALSE) -> 230000 | I15: =H15*G15 -> 1150000 | J15: NEQUI
B16: 46278 | C16: T-0015 | D16: 8 | E16: =VLOOKUP(D16,Productos!$B$6:$C$35,2,FALSE) -> PARLANTE BLUETOOTH | F16: =VLOOKUP(D16,Productos!$B$6:$D$35,3,FALSE) -> AUDIO | G16: 2 | H16: =VLOOKUP(D16,Productos!$B$6:$E$35,4,FALSE) -> 160000 | I16: =H16*G16 -> 320000 | J16: EFECTIVO
B17: 46278 | C17: T-0016 | D17: 26 | E17: =VLOOKUP(D17,Productos!$B$6:$C$35,2,FALSE) -> SMARTWATCH BASICO | F17: =VLOOKUP(D17,Productos!$B$6:$D$35,3,FALSE) -> WEARABLES | G17: 5 | H17: =VLOOKUP(D17,Productos!$B$6:$E$35,4,FALSE) -> 180000 | I17: =H17*G17 -> 900000 | J17: TARJETA
... B156: 46430 | C156: T-0155 | D156: 3 | E156: =VLOOKUP(D156,Productos!$B$6:$C$35,2,FALSE) -> TECLADO ALAMBRICO | F156: =VLOOKUP(D156,Productos!$B$6:$D$35,3,FALSE) -> ACCESORIOS PC | G156: 4 | H156: =VLOOKUP(D156,Productos!$B$6:$E$35,4,FALSE) -> 60000 | I156: =H156*G156 -> 240000 | J156: TARJETA

Sheet Reporte
B4: Etiquetas de fila | C4: Suma de PRECIO TOTAL
B5: ACCESORIOS | C5: 550000
B6: ACCESORIOS MOVIL | C6: 1450000
B7: ACCESORIOS PC | C7: 5705000
B8: ALMACENAMIENTO | C8: 8695000
B9: AUDIO | C9: 7620000
B10: CABLES | C10: 630000
B11: CAMARA | C11: 240000
B12: ENERGIA | C12: 4330000
B13: HOGAR/OFICINA | C13: 14520000
B14: MONITORES | C14: 5720000
B15: REDES | C15: 2811000
B16: WEARABLES | C16: 5820000
B17: Total general | C17: 58091000
Q25: Etiquetas de fila | R25: Suma de PRECIO TOTAL
Q26: DAVIPLATA | R26: 16984000
Q27: EFECTIVO | R27: 14105000
B28: Etiquetas de fila | C28: Suma de PRECIO TOTAL | Q28: NEQUI | R28: 12574000
B29: AUDIFONOS ALAMBRICOS | C29: 840000 | Q29: TARJETA | R29: 14428000
B30: AUDIFONOS BLUETOOTH | C30: 1200000 | Q30: Total general | R30: 58091000
B31: BANDA FITNESS | C31: 2040000
B32: BASE ENFRIADORA LAPTOP | C32: 1275000
B33: CABLE HDMI 2MTS | C33: 300000
B34: CABLE USB-C | C34: 330000
B35: CARGADOR RAPIDO USB-C | C35: 1170000
B36: DIADEMA GAMER | C36: 2700000
B37: DISCO SSD 1TB | C37: 4370000
B38: DISCO SSD 480GB | C38: 3150000
B39: EXTENSOR WIFI | C39: 1950000
B40: FUNDA PARA CELULAR | C40: 570000
B41: HUB USB 4 PUERTOS | C41: 550000
B42: IMPRESORA BASICA | C42: 13440000
... B59: Total general | C59: 58091000
